Metadata-Version: 1.1
Name: dympy
Version: 0.0.3
Summary: Python-Dymola communication on windows
Home-page: https://github.com/BrechtBa/dympy
Author: Brecht Baeten
Author-email: brecht.baeten@gmail.com
License: MIT
Platform: UNKNOWN
Classifier: Programming Language :: Python :: 2.7
